ps2controller.py
circuitpython_ps2controller-1.2.2.dist-info/LICENSE
circuitpython_ps2controller-1.2.2.dist-info/METADATA
circuitpython_ps2controller-1.2.2.dist-info/WHEEL
circuitpython_ps2controller-1.2.2.dist-info/top_level.txt
circuitpython_ps2controller-1.2.2.dist-info/RECORD
