Metadata-Version: 2.1
Name: circuitpython-ps2controller
Version: 1.2.2
Summary: CircuitPython library to read Sony PS2 game controllers
Author-email: Tod Kurt <tod@todbot.com>
License: MIT
Project-URL: Homepage, https://github.com/todbot/CircuitPython_PS2Controller
Keywords: adafruit,blinka,circuitpython,micropython,ps2controller,ps2,psx,controller,gamepad,sony,dualshock
Classifier: Intended Audience :: Developers
Classifier: Topic :: Software Development :: Libraries
Classifier: Topic :: Software Development :: Embedded Systems
Classifier: Topic :: System :: Hardware
Classifier: License :: OSI Approved :: MIT License
Classifier: Programming Language :: Python :: 3
License-File: LICENSE
Requires-Dist: Adafruit-Blinka
Provides-Extra: optional
